odoo/addons/sale_order_line_cancel_sale_stock/README.rst
odoo/addons/sale_order_line_cancel_sale_stock/__init__.py
odoo/addons/sale_order_line_cancel_sale_stock/__manifest__.py
odoo/addons/sale_order_line_cancel_sale_stock/i18n/sale_order_line_cancel_sale_stock.pot
odoo/addons/sale_order_line_cancel_sale_stock/models/__init__.py
odoo/addons/sale_order_line_cancel_sale_stock/models/sale_order.py
odoo/addons/sale_order_line_cancel_sale_stock/models/sale_order_line.py
odoo/addons/sale_order_line_cancel_sale_stock/models/stock_move.py
odoo/addons/sale_order_line_cancel_sale_stock/readme/CONTRIBUTORS.rst
odoo/addons/sale_order_line_cancel_sale_stock/readme/DESCRIPTION.rst
odoo/addons/sale_order_line_cancel_sale_stock/static/description/icon.png
odoo/addons/sale_order_line_cancel_sale_stock/static/description/index.html
odoo/addons/sale_order_line_cancel_sale_stock/tests/__init__.py
odoo/addons/sale_order_line_cancel_sale_stock/tests/common.py
odoo/addons/sale_order_line_cancel_sale_stock/tests/test_sale_order_line_cancel.py
odoo_addon_sale_order_line_cancel_sale_stock-16.0.2.0.0.dist-info/METADATA
odoo_addon_sale_order_line_cancel_sale_stock-16.0.2.0.0.dist-info/WHEEL
odoo_addon_sale_order_line_cancel_sale_stock-16.0.2.0.0.dist-info/top_level.txt
odoo_addon_sale_order_line_cancel_sale_stock-16.0.2.0.0.dist-info/RECORD
